MANIFEST.in
README.rst
requirements.txt
setup.cfg
setup.py
rnkrcli/__init__.py
rnkrcli/consts.py
rnkrcli/rnkrsvc.py
rnkrcli/tasks.py
rnkrcli/utils.py
rnkrcli.egg-info/PKG-INFO
rnkrcli.egg-info/SOURCES.txt
rnkrcli.egg-info/dependency_links.txt
rnkrcli.egg-info/requires.txt
rnkrcli.egg-info/top_level.txt
rnkrcli/bin/rnkr
rnkrcli/templates/app.py.tpl
rnkrcli/templates/app.r.tpl
rnkrcli/templates/config.rnkr.python.tpl
rnkrcli/templates/config.rnkr.r.tpl
rnkrcli/templates/requirements.txt.tpl