Metadata-Version: 1.0
Name: rnkrcli
Version: 9.0
Summary: RNKR Client Interface
Home-page: https://rnkr.io
Author: Isaac Elbaz
Author-email: isaac@rnkr.io
License: UNKNOWN
Keywords: rnkr,rnkr client,rnkrcli
Platform: UNKNOWN
